classwork/__init__.py
classwork/main.py
classwork/utils.py
classwork-0.0.7.dist-info/LICENSE.md
classwork-0.0.7.dist-info/METADATA
classwork-0.0.7.dist-info/WHEEL
classwork-0.0.7.dist-info/RECORD
