Metadata-Version: 2.1
Name: classwork
Version: 0.0.7
Summary: A simple Python module to help distribute you tasks across multiple brokers as microservices
License: MIT
Author: Anthony Mugendi
Author-email: ngurumugz@gmail.com
Requires-Python: >=3.8,<4.0
Classifier: License :: OSI Approved :: MIT License
Classifier: Programming Language :: Python :: 3
Classifier: Programming Language :: Python :: 3.8
Classifier: Programming Language :: Python :: 3.9
Classifier: Programming Language :: Python :: 3.10
Classifier: Programming Language :: Python :: 3.11
Requires-Dist: hashids (==1.3.1)
Requires-Dist: nats-py (==2.2.0)
Requires-Dist: numpy (>=1.24.3,<2.0.0)
Requires-Dist: termcolor2 (>=0.0.3,<0.0.4)
Requires-Dist: typjson (==0.0.32)
